but_info_maths/__init__.py
but_info_maths/pivot_gauss.py
but_info_maths-0.0.10.dist-info/licenses/LICENSE
but_info_maths-0.0.10.dist-info/METADATA
but_info_maths-0.0.10.dist-info/WHEEL
but_info_maths-0.0.10.dist-info/top_level.txt
but_info_maths-0.0.10.dist-info/RECORD
