Metadata-Version: 2.4
Name: but-info-maths
Version: 0.0.10
Summary: Outils pour l'enseignement des maths en BUT d'informatique
Author-email: Matthieu Bensussan <matthieu.bensussan@gmail.com>
License-Expression: MIT
Classifier: Programming Language :: Python :: 3
Classifier: Operating System :: OS Independent
Requires-Python: >=3.9
License-File: LICENSE
Dynamic: license-file
